<varlistentry>
  <term><option>leftupdown</option></term>
  <listitem>
    <para>
      The script to run to adjust routing and/or firewalling when the
      status of the connection changes (default <command>ipsec
      _updown</command>).  May include positional parameters separated
      by white space (although this requires enclosing the whole
      string in quotes); including shell metacharacters is unwise.  An
      example to enable routing when using the XFRM stack, one can
      use:
    </para>
    <para>
      <simplelist columns='1'>
        <member><computeroutput>updown="ipsec _updown --route yes"</computeroutput></member>
      </simplelist>
    </para>
    <para>
      To disable calling an updown script, set it to the empty string,
      eg leftupdown="" or leftupdown="%disabled".
    </para>
    <para>
      Connections with type= set to passthrough, reject or drop never run updown.
    </para>
    <para>
      See
      <citerefentry><refentrytitle>libreswan</refentrytitle><manvolnum>7</manvolnum></citerefentry>
      for details.
    </para>
    <para>
      Relevant only locally, other end need not agree on it.
    </para>
  </listitem>
</varlistentry>
